{
    "optimizerUsed": "SMD",
    "solutionDistance": 1079.0,
    "computationalTime(s)": 0.124,
    "solution": {
        "1": [
            {
                "orders": [
                    "16",
                    "17",
                    "18",
                    "19"
                ],
                "pickRoute": [
                    "137",
                    "119",
                    "135",
                    "122",
                    "143",
                    "121",
                    "133",
                    "120",
                    "141",
                    "124",
                    "145",
                    "134",
                    "147",
                    "118",
                    "149",
                    "151",
                    "125",
                    "148",
                    "128",
                    "142",
                    "117",
                    "140",
                    "152",
                    "127",
                    "138",
                    "129",
                    "132",
                    "126",
                    "130",
                    "131",
                    "136",
                    "146",
                    "139",
                    "150",
                    "123",
                    "144"
                ]
            },
            {
                "orders": [
                    "10",
                    "9",
                    "8",
                    "6"
                ],
                "pickRoute": [
                    "60",
                    "84",
                    "67",
                    "62",
                    "74",
                    "73",
                    "87",
                    "54",
                    "82",
                    "77",
                    "70",
                    "72",
                    "69",
                    "85",
                    "86",
                    "83",
                    "75",
                    "58",
                    "55",
                    "65",
                    "68",
                    "61",
                    "63",
                    "64",
                    "78",
                    "76",
                    "79",
                    "71",
                    "59",
                    "66",
                    "80",
                    "81"
                ]
            },
            {
                "orders": [
                    "12",
                    "13",
                    "14",
                    "15"
                ],
                "pickRoute": [
                    "103",
                    "102",
                    "112",
                    "104",
                    "94",
                    "100",
                    "97",
                    "113",
                    "115",
                    "106",
                    "98",
                    "105",
                    "111",
                    "110",
                    "96",
                    "101",
                    "116",
                    "108",
                    "109",
                    "95",
                    "107",
                    "114",
                    "99"
                ]
            },
            {
                "orders": [
                    "20",
                    "7",
                    "5",
                    "4"
                ],
                "pickRoute": [
                    "45",
                    "42",
                    "52",
                    "38",
                    "33",
                    "37",
                    "39",
                    "40",
                    "154",
                    "44",
                    "153",
                    "56",
                    "57",
                    "51",
                    "36",
                    "41",
                    "49",
                    "53",
                    "50",
                    "48",
                    "34",
                    "35",
                    "43",
                    "47",
                    "46"
                ]
            },
            {
                "orders": [
                    "1",
                    "2",
                    "3",
                    "11"
                ],
                "pickRoute": [
                    "5",
                    "16",
                    "15",
                    "29",
                    "7",
                    "3",
                    "21",
                    "27",
                    "28",
                    "17",
                    "6",
                    "9",
                    "30",
                    "22",
                    "12",
                    "18",
                    "10",
                    "25",
                    "13",
                    "2",
                    "20",
                    "26",
                    "8",
                    "19",
                    "14",
                    "90",
                    "92",
                    "93",
                    "88",
                    "89",
                    "91",
                    "4",
                    "23",
                    "31",
                    "11",
                    "24",
                    "32"
                ]
            }
        ]
    }
}