{
    "optimizerUsed": "SMD",
    "solutionDistance": 1922.9999999999998,
    "computationalTime(s)": 0.125,
    "solution": {
        "1": [
            {
                "orders": [
                    "9",
                    "10",
                    "14",
                    "16"
                ],
                "pickRoute": [
                    "63",
                    "73",
                    "71",
                    "47",
                    "77",
                    "44",
                    "46",
                    "76",
                    "70",
                    "64",
                    "43",
                    "67",
                    "72",
                    "66",
                    "62",
                    "45",
                    "74",
                    "65",
                    "75"
                ]
            },
            {
                "orders": [
                    "20",
                    "15",
                    "13",
                    "12"
                ],
                "pickRoute": [
                    "61",
                    "50",
                    "56",
                    "57",
                    "58",
                    "55",
                    "68",
                    "52",
                    "51",
                    "53",
                    "60",
                    "54",
                    "69",
                    "59",
                    "96",
                    "98",
                    "97",
                    "94",
                    "95"
                ]
            },
            {
                "orders": [
                    "1",
                    "2",
                    "3",
                    "5"
                ],
                "pickRoute": [
                    "9",
                    "28",
                    "2",
                    "3",
                    "4",
                    "19",
                    "11",
                    "6",
                    "7",
                    "5",
                    "12",
                    "16",
                    "10",
                    "8",
                    "14",
                    "29",
                    "18",
                    "20",
                    "13",
                    "17",
                    "15"
                ]
            },
            {
                "orders": [
                    "22",
                    "21",
                    "19",
                    "18"
                ],
                "pickRoute": [
                    "86",
                    "88",
                    "99",
                    "83",
                    "108",
                    "93",
                    "102",
                    "110",
                    "85",
                    "111",
                    "109",
                    "101",
                    "90",
                    "105",
                    "92",
                    "87",
                    "106",
                    "91",
                    "89",
                    "107",
                    "104",
                    "84",
                    "100",
                    "103"
                ]
            },
            {
                "orders": [
                    "11",
                    "24",
                    "26",
                    "30"
                ],
                "pickRoute": [
                    "152",
                    "128",
                    "154",
                    "151",
                    "130",
                    "49",
                    "129",
                    "122",
                    "48",
                    "131",
                    "119",
                    "127",
                    "121",
                    "126",
                    "155",
                    "118",
                    "150",
                    "120",
                    "153"
                ]
            },
            {
                "orders": [
                    "8",
                    "7",
                    "6",
                    "4"
                ],
                "pickRoute": [
                    "30",
                    "42",
                    "21",
                    "41",
                    "36",
                    "23",
                    "37",
                    "40",
                    "25",
                    "31",
                    "24",
                    "32",
                    "38",
                    "33",
                    "22",
                    "27",
                    "34",
                    "35",
                    "39",
                    "26"
                ]
            },
            {
                "orders": [
                    "25",
                    "27",
                    "28",
                    "29"
                ],
                "pickRoute": [
                    "145",
                    "141",
                    "138",
                    "147",
                    "123",
                    "135",
                    "133",
                    "139",
                    "134",
                    "143",
                    "142",
                    "140",
                    "124",
                    "137",
                    "136",
                    "149",
                    "146",
                    "132",
                    "144",
                    "125",
                    "148"
                ]
            },
            {
                "orders": [
                    "23",
                    "17"
                ],
                "pickRoute": [
                    "79",
                    "113",
                    "117",
                    "116",
                    "80",
                    "114",
                    "112",
                    "81",
                    "115",
                    "78",
                    "82"
                ]
            }
        ]
    }
}