{
    "optimizerUsed": "COG",
    "solutionDistance": 1667.0,
    "computationalTime(s)": 0.08,
    "solution": {
        "1": [
            {
                "orders": [
                    "4",
                    "14",
                    "15",
                    "20"
                ],
                "pickRoute": [
                    "62",
                    "13",
                    "12",
                    "44",
                    "43",
                    "61",
                    "46",
                    "45"
                ]
            },
            {
                "orders": [
                    "12",
                    "10",
                    "7",
                    "2"
                ],
                "pickRoute": [
                    "6",
                    "21",
                    "32",
                    "31",
                    "7",
                    "23",
                    "37",
                    "38",
                    "22",
                    "36"
                ]
            },
            {
                "orders": [
                    "32",
                    "35",
                    "36",
                    "37"
                ],
                "pickRoute": [
                    "114",
                    "116",
                    "115",
                    "111",
                    "110",
                    "100",
                    "112",
                    "117",
                    "97",
                    "118",
                    "113",
                    "98",
                    "99",
                    "109"
                ]
            },
            {
                "orders": [
                    "28",
                    "25",
                    "23",
                    "21"
                ],
                "pickRoute": [
                    "70",
                    "74",
                    "84",
                    "64",
                    "69",
                    "83",
                    "63",
                    "76",
                    "68",
                    "75"
                ]
            },
            {
                "orders": [
                    "11",
                    "16",
                    "17",
                    "19"
                ],
                "pickRoute": [
                    "53",
                    "34",
                    "51",
                    "49",
                    "60",
                    "52",
                    "35",
                    "47",
                    "58",
                    "33",
                    "59",
                    "50",
                    "48"
                ]
            },
            {
                "orders": [
                    "40",
                    "39",
                    "38",
                    "31"
                ],
                "pickRoute": [
                    "93",
                    "96",
                    "124",
                    "120",
                    "128",
                    "123",
                    "122",
                    "129",
                    "121",
                    "126",
                    "125",
                    "94",
                    "95",
                    "119",
                    "127"
                ]
            },
            {
                "orders": [
                    "13",
                    "18",
                    "24",
                    "27"
                ],
                "pickRoute": [
                    "82",
                    "80",
                    "54",
                    "72",
                    "42",
                    "39",
                    "57",
                    "41",
                    "40",
                    "56",
                    "55",
                    "79",
                    "71",
                    "81",
                    "73"
                ]
            },
            {
                "orders": [
                    "8",
                    "6",
                    "5",
                    "1"
                ],
                "pickRoute": [
                    "3",
                    "20",
                    "14",
                    "24",
                    "25",
                    "4",
                    "17",
                    "16",
                    "19",
                    "2",
                    "26",
                    "15",
                    "18",
                    "5"
                ]
            },
            {
                "orders": [
                    "22",
                    "26",
                    "29",
                    "30"
                ],
                "pickRoute": [
                    "86",
                    "65",
                    "66",
                    "89",
                    "85",
                    "91",
                    "90",
                    "88",
                    "92",
                    "87",
                    "77",
                    "67",
                    "78"
                ]
            },
            {
                "orders": [
                    "34",
                    "33",
                    "9",
                    "3"
                ],
                "pickRoute": [
                    "106",
                    "107",
                    "104",
                    "103",
                    "9",
                    "8",
                    "30",
                    "11",
                    "29",
                    "28",
                    "27",
                    "10",
                    "102",
                    "105",
                    "108",
                    "101"
                ]
            }
        ]
    }
}